inso_toolbox/__init__.py
inso_toolbox/detectors/__init__.py
inso_toolbox/detectors/drift_detector.py
inso_toolbox/detectors/oscillation_detector.py
inso_toolbox/detectors/utils/__init__.py
inso_toolbox/detectors/utils/visualization.py
inso_toolbox/geometry/__init__.py
inso_toolbox/geometry/vessel.py
inso_toolbox/physics/__init__.py
inso_toolbox/physics/dimensionless/__init__.py
inso_toolbox/physics/dimensionless/dimensionless.py
inso_toolbox/physics/dynamic_limit_sep/__init__.py
inso_toolbox/physics/dynamic_limit_sep/fluid_momentum.py
inso_toolbox/physics/dynamic_limit_sep/psv.py
inso_toolbox/physics/dynamic_limit_sep/vane_pack.py
inso_toolbox/physics/single_phase/__init__.py
inso_toolbox/physics/single_phase/darcy_friction.py
inso_toolbox/physics/single_phase/single_phase.py
inso_toolbox/physics/steady_state.py
inso_toolbox/pipeline.py
inso_toolbox/quality/__init__.py
inso_toolbox/signal/__init__.py
inso_toolbox/signal/butter.py
inso_toolbox/signal/chebyshev.py
inso_toolbox/signal/interpolate.py
inso_toolbox/signal/sg.py
inso_toolbox/ts_utils/__init__.py
inso_toolbox/ts_utils/time_series.py
inso_toolbox/units/__init__.py
inso_toolbox/units/convert.py
inso_toolbox/units/convert_from_cdf.py
inso_toolbox/units/units.py
inso_toolbox/units/utils/converter_class.py
inso_toolbox/units/utils/unit_class.py
inso_toolbox/units/utils/unit_group_class.py
inso_toolbox/units/utils/units_class.py
inso_toolbox/units/utils/units_docstring.py
inso_toolbox/utils/__init__.py
inso_toolbox/utils/helpers.py
inso_toolbox/utils/pipeline_decorator.py
inso_toolbox/utils/toy_data.py
cognite_inso_toolbox-3.0.5.dist-info/LICENSE
cognite_inso_toolbox-3.0.5.dist-info/WHEEL
cognite_inso_toolbox-3.0.5.dist-info/METADATA
cognite_inso_toolbox-3.0.5.dist-info/RECORD
