Metadata-Version: 2.1
Name: cognite-inso-toolbox
Version: 3.0.5
Summary: Inso Toolbox
Author: cognite
Author-email: gustavo.zarruk@cognite.com, johannes.kolberg@cognite.com, nicolas.agnes@cognite.com, angela.atkinson@cognite.com
Requires-Python: >=3.7,<3.10
Classifier: Programming Language :: Python :: 3
Classifier: Programming Language :: Python :: 3.7
Classifier: Programming Language :: Python :: 3.8
Classifier: Programming Language :: Python :: 3.9
Requires-Dist: cognite-sdk (>=2.6.2,<3.0.0)
Requires-Dist: matplotlib (>=3.3.0,<4.0.0)
Requires-Dist: numba (>=0.52.0)
Requires-Dist: scipy (>=1.4.1,<2.0.0)
